django_email_hijacker-0.3.2.dist-info/DESCRIPTION.rst
django_email_hijacker-0.3.2.dist-info/METADATA
django_email_hijacker-0.3.2.dist-info/metadata.json
django_email_hijacker-0.3.2.dist-info/RECORD
django_email_hijacker-0.3.2.dist-info/top_level.txt
django_email_hijacker-0.3.2.dist-info/WHEEL
email_hijacker/__init__.py
email_hijacker/apps.py
email_hijacker/defaults.py
email_hijacker/backends/__init__.py
email_hijacker/backends/hijacker.py
