Metadata-Version: 2.0
Name: django-email-hijacker
Version: 0.3.2
Summary: Email Hijacker for Django
Home-page: https://github.com/OohlaLabs/django-email-hijacker
Author: Thierry Jossermoz
Author-email: thierry.jossermoz@oohlalabs.com
License: MIT
Platform: UNKNOWN
Classifier: Development Status :: 3 - Alpha
Classifier: Environment :: Web Environment
Classifier: Intended Audience :: Developers
Classifier: Operating System :: OS Independent
Classifier: Programming Language :: Python
Classifier: Programming Language :: Python :: 2.7
Classifier: Programming Language :: Python :: 3.3
Classifier: Programming Language :: Python :: 3.4
Classifier: Topic :: Software Development :: Libraries :: Python Modules
Classifier: Framework :: Django
Requires-Dist: Django (>=1.5)
Requires-Dist: django-pods (>=1.0)
